doclick/__init__.py
doclick/doclick_core.py
doclick/doclick_image.py
doclick-0.1.7.dist-info/LICENSE
doclick-0.1.7.dist-info/METADATA
doclick-0.1.7.dist-info/WHEEL
doclick-0.1.7.dist-info/top_level.txt
doclick-0.1.7.dist-info/RECORD
